Bladex/__init__.py
Bladex/__ext__/B3DLib.py
Bladex/__ext__/BBLibc.py
Bladex/__ext__/BInputc.py
Bladex/__ext__/BUIxc.py
Bladex/__ext__/Console.py
Bladex/__ext__/Raster.py
Bladex/__ext__/Traps_C.py
Bladex/__ext__/netgame.py
Bladex/__sub__/b_object.py
Bladex/__sub__/b_types.py
Bladex/__sub__/character.py
Bladex/__sub__/dllexport.py
Bladex/__sub__/entity.py
Bladex/__sub__/inventory.py
Bladex-1.0.5.dist-info/LICENSE
Bladex-1.0.5.dist-info/METADATA
Bladex-1.0.5.dist-info/WHEEL
Bladex-1.0.5.dist-info/top_level.txt
Bladex-1.0.5.dist-info/RECORD
