Metadata-Version: 2.1
Name: Bladex
Version: 1.0.5
Summary: The Blade of Darkness virtual Python module for code completion and type hints
Author-email: Sryml <sryml@hotmail.com>
Project-URL: Homepage, https://github.com/Sryml/blade-virtual-module
Project-URL: Bug Tracker, https://github.com/Sryml/blade-virtual-module/issues
Keywords: Blade of Darkness,code completion,type hints
Classifier: Topic :: Text Editors :: Integrated Development Environments (IDE)
Classifier: License :: OSI Approved :: MIT License
Classifier: Programming Language :: Python
Classifier: Programming Language :: Python :: 3
Requires-Python: >=3.8
License-File: LICENSE
